livekit/plugins/aws/__init__.py
livekit/plugins/aws/llm.py
livekit/plugins/aws/log.py
livekit/plugins/aws/models.py
livekit/plugins/aws/py.typed
livekit/plugins/aws/stt.py
livekit/plugins/aws/tts.py
livekit/plugins/aws/utils.py
livekit/plugins/aws/version.py
livekit/plugins/aws/experimental/realtime/__init__.py
livekit/plugins/aws/experimental/realtime/events.py
livekit/plugins/aws/experimental/realtime/pretty_printer.py
livekit/plugins/aws/experimental/realtime/realtime_model.py
livekit/plugins/aws/experimental/realtime/turn_tracker.py
livekit/plugins/aws/experimental/realtime/types.py
livekit_plugins_aws-1.3.11.dist-info/METADATA
livekit_plugins_aws-1.3.11.dist-info/WHEEL
livekit_plugins_aws-1.3.11.dist-info/RECORD
