Metadata-Version: 2.4
Name: livekit-plugins-aws
Version: 1.3.11
Summary: LiveKit Agents Plugin for services from AWS
Project-URL: Documentation, https://docs.livekit.io
Project-URL: Website, https://livekit.io/
Project-URL: Source, https://github.com/livekit/agents
Author-email: LiveKit <hello@livekit.io>
License-Expression: Apache-2.0
Keywords: ai,audio,aws,livekit,nova,realtime,sonic,video,voice
Classifier: Intended Audience :: Developers
Classifier: License :: OSI Approved :: Apache Software License
Classifier: Programming Language :: Python :: 3
Classifier: Programming Language :: Python :: 3 :: Only
Classifier: Programming Language :: Python :: 3.9
Classifier: Programming Language :: Python :: 3.10
Classifier: Programming Language :: Python :: 3.12
Classifier: Topic :: Multimedia :: Sound/Audio
Classifier: Topic :: Multimedia :: Video
Classifier: Topic :: Scientific/Engineering :: Artificial Intelligence
Requires-Python: >=3.9.0
Requires-Dist: aioboto3>=14.1.0
Requires-Dist: aws-sdk-transcribe-streaming>=0.2.0; python_version >= '3.12'
Requires-Dist: livekit-agents>=1.3.11
Provides-Extra: realtime
Requires-Dist: aws-sdk-bedrock-runtime>=0.2.0; (python_version >= '3.12') and extra == 'realtime'
Requires-Dist: aws-sdk-signers>=0.0.3; (python_version >= '3.12') and extra == 'realtime'
Requires-Dist: boto3>1.35.10; extra == 'realtime'
